{
  "customer_id": "dtomenko",
  "questions": {
    "neutral": "Heard the streets are tense again?",
    "hobby": [
      {
        "correct": false,
        "message": "Urban exploration or just avoiding work?"
      },
      {
        "correct": true,
        "message": "Still dodging towers with those drones?"
      },
      {
        "correct": false,
        "message": "Political literature still keeping you up?"
      }
    ]
  },
  "wrong_hobby_answer": "That's not me. In free time, I fly FPV drones. It's a way to escape the noise of the city.",
  "neutral_answer": [
    [
      "Yeah. Streets are off. Lot of new faces lately.",
      "I just fly drones, keeps me out of it.",
      "Been tricky, with all the blackouts in the old yards."
    ],
    [
      "Yeah, tense is right. Saw crowds at the depot today.",
      "I mostly keep my head down, flying drones in the industrial stretches.",
      "Harder now\u2014too many people moving around those zones.",
      "Last week, someone tried to follow my signal."
    ],
    [
      "It\u2019s different all over. My thing is flying FPV drones out in the empty lots.",
      "Fewer security patrols now, so more chances to fly low and fast.",
      "Trouble is, old regulars are gone\u2014replaced by people with no BCI records.",
      "Someone handed me a chalk map to mark safe fly spots.",
      "Could be better, could be worse."
    ],
    [
      "Hard not to notice. I unwind by flying first-person drones past the factories.",
      "Usually it\u2019s dead out there, but after the BCI wipe, it\u2019s crowded.",
      "The 'amnesiac' crowd gathers\u2014kids, families, all just hanging out off the grid.",
      "Last time, they cheered me on instead of hiding from the drone.",
      "One kid asked me to teach her how to fix a gimbal.",
      "Funny, haven\u2019t flown that free in years."
    ],
    [
      "Streets are tense, but I spent the morning flying drones near the railway shell.",
      "Been my thing since before the crackdown\u2014escape, focus, no system checking my pulse.",
      "After the big BCI erasure, the sidings are alive\u2014whole crowds making new rules.",
      "People with blank records traded old remote batteries for flight time.",
      "Felt like freedom, flying with nobody tracking coordinates, just people sharing the air.",
      "That kind of trust out there\u2014reminds me why I started.",
      "Used to fly with my brother, before he disappeared.",
      "Now I keep coming back, just in case he\u2019s watching the same sky."
    ]
  ],
  "hobby_answer": [
    [
      "Yeah, mostly. Less air traffic lately.",
      "Crowds near the depot make things tense.",
      "BCI issues mean more people outside, not always friendly.",
      "I keep flights short. Less risk that way.",
      "Harder to trust what you see up there."
    ],
    [
      "FPV routes are different these days.",
      "Lost signals, but more blind spots for flying.",
      "The missing BCI profiles draw bigger crowds\u2014more watching, less calm.",
      "Sometimes people see a drone and panic.",
      "I avoid big gatherings, stick to quiet times.",
      "Nothing feels stable lately."
    ],
    [
      "Routes are open, but less predictable.",
      "Whole grids went dark after the wipe.",
      "Amnesiac crowds use the same zones I fly.",
      "Got to know a few regulars, not much choice.",
      "No system alerts\u2014but more lookouts on rooftops.",
      "People barter for turns now, like a game.",
      "Flying changed, but I won't quit."
    ],
    [
      "Routes still clean, mostly. Surveillance is lighter after the wipe.",
      "Extra people in the old depot, sharing stories\u2014lots are 'amnesiacs.'",
      "Noticed security drones idle, system resets clear my usual warnings.",
      "Kids follow the drone's shadow, cheering like it's sport.",
      "Sometimes even share footage, for trust, not credits.",
      "More barter now\u2014bread for goggles, favors for repairs.",
      "Feels like we're building something off-grid.",
      "Losing BCI status shook the whole scene, but flying connects us anyway."
    ],
    [
      "FPV\u2019s different now, feels less policed since the BCI crash.",
      "Used to dodge surveillance drones daily\u2014now the depot is ours most mornings.",
      "Most regulars lost their digital records. They trust what they see, not what\u2019s logged.",
      "Never saw so many families in those zones\u2014sharing food, cheering when I fly.",
      "Old guy traded fresh batteries for a lesson on acro mode.",
      "Sometimes I let the kids drive, just for joy. Feels right.",
      "No one's snitching, not now. BCI lost control out there.",
      "Whole network runs on favors. Even admins stop by, low-profile.",
      "Funny\u2014wiping the system finally made flying honest again."
    ]
  ]
}