{
  "title": "The Reckoning Tribunal",
  "story_summary": "In the city of Stenograd, where governance had become invisible machinery guided by the all-seeing Behavioral Compliance Index, the sudden, secretive death of its architect, Marek Halden, set off a chain reaction no one could control. As glitches in Halden's intricate system began reassigning citizens to baffling new roles - placing elite, trusted residents in menial tasks and outcasts in positions of power - chaos took root. Council factions turned on each other, public confidence fractured, and, in the confusion, citizens who had slipped through the system's net resurfaced, weaving new underground networks and exploiting every weakness. Paranoia and suspicion gripped the city as hacked BCI scores sent privileges and restrictions ricocheting wildly. Things reached a breaking point when a blackout revealed a haunting mural of Halden unraveling his own shadow, becoming a rallying cry against the unseen algorithms that ruled them all. Unrest swelled as Innovators unearthed 'The Ledger,' a record of the BCI's silent cruelties, unleashing a wave of anguish and defiance. Forced into daylight, the Council launched a tribunal, where a reluctant whistleblower, Oksana Lintz, exposed the truth, leaving Stenograd forever changed - order superficially restored, but trust in the system irrevocably broken.",
  "timestamp": "2025-06-10T19:48:00",
  "news": {
    "official": [
      {
        "image_id": "faulty_projection",
        "headline": "City Tribunal Begins",
        "anchor_line": "The Council launches a citywide tribunal investigating the Behavioral Compliance Index - Stenograd's real-time resident scoring system.",
        "contextual_reframing": "Transparent review ensures public trust in our advanced governance tools and ongoing civic stability."
      },
      {
        "image_id": "mirror_fragment",
        "headline": "Whistleblower Testimony Heard",
        "anchor_line": "Key witness Oksana Lintz shares evidence of wrongly applied sanctions under the BCI at today's public hearing.",
        "contextual_reframing": "Stenograd remains committed to accuracy and fair treatment for all citizens in system operations."
      },
      {
        "image_id": "paper_stack",
        "headline": "Reparations Announced",
        "anchor_line": "The tribunal promises partial reparations for residents affected by BCI errors, reinforcing redress and recovery.",
        "contextual_reframing": "The Council's swift action exemplifies adaptive, self-correcting governance aligned with technocratic values."
      }
    ],
    "underground": [
      {
        "image_id": "shattered_display",
        "headline": "BCI On Trial",
        "anchor_line": "Council tries to fix the Behavioral Compliance Index mess - only after public outrage boiled over.",
        "contextual_reframing": "The BCI system tracks every move and scores us all. Now the cracks are too big to hide. Tribunal isn't justice - it's damage control."
      },
      {
        "image_id": "interrogation_reflection",
        "headline": "Whistleblower Unmasked",
        "anchor_line": "Oksana Lintz steps up, but faces the tribunal's glare for exposing wrongful BCI punishments.",
        "contextual_reframing": "She risked everything to say the obvious: the system is broken by design. But heroes here get blamed while officials wash their hands."
      },
      {
        "image_id": "empty_bench",
        "headline": "Empty Promises Again",
        "anchor_line": "Leaders promise reparations for BCI victims - no dates, no details, just headlines.",
        "contextual_reframing": "We've seen these scripted gestures before. Council covers itself, but justice for the flagged and silenced rarely comes. Don't let them decide when 'enough' is enough."
      }
    ]
  },
  "visitors": [
    "olintz",
    "shalek",
    "npetrak",
    "dtomenko"
  ],
  "character_stats": {
    "olintz": {
      "bci_score": 25,
      "political_preference": "innovators",
      "bci_history": [
        39,
        34,
        34,
        38,
        41,
        45,
        50,
        55,
        51,
        47,
        52,
        34,
        29,
        24,
        22,
        5,
        25
      ]
    },
    "npetrak": {
      "bci_score": 49,
      "political_preference": "harmonists",
      "bci_history": [
        75,
        78,
        74,
        75,
        77,
        76,
        79,
        79,
        75,
        70,
        75,
        69,
        63,
        59,
        55,
        52,
        49
      ]
    },
    "dtomenko": {
      "bci_score": 56,
      "political_preference": "innovators",
      "bci_history": [
        81,
        77,
        73,
        76,
        74,
        69,
        69,
        64,
        62,
        64,
        67,
        65,
        61,
        61,
        61,
        58,
        56
      ]
    },
    "lkova": {
      "bci_score": 20,
      "political_preference": "directorate",
      "bci_history": [
        82,
        77,
        74,
        71,
        71,
        67,
        66,
        65,
        64,
        62,
        59,
        56,
        52,
        48,
        29,
        24,
        20
      ]
    },
    "shalek": {
      "bci_score": 35,
      "political_preference": "directorate",
      "bci_history": [
        99,
        94,
        92,
        96,
        91,
        94,
        96,
        91,
        87,
        82,
        82,
        80,
        63,
        45,
        41,
        37,
        35
      ]
    },
    "rmiskovic": {
      "bci_score": 21,
      "political_preference": "rebel",
      "bci_history": [
        40,
        43,
        47,
        47,
        47,
        46,
        43,
        46,
        42,
        41,
        40,
        37,
        32,
        28,
        24,
        24,
        21
      ]
    }
  },
  "chats": {
    "olintz": {
      "opener": {
        "customer_id": "olintz",
        "questions": {
          "neutral": "You look like you dodged something - true?",
          "hobby": [
            {
              "correct": true,
              "message": "Origami's still better than meds, huh?"
            },
            {
              "correct": false,
              "message": "That camera still your favorite weapon?"
            },
            {
              "correct": false,
              "message": "You still collecting typewriters?"
            }
          ]
        },
        "wrong_hobby_answer": "That's not me. In free time, I fold origami... from scrap forms mostly. It helps me think... quietly.",
        "neutral_answer": [
          [
            "Maybe. It's been a tense week, everyone looks over their shoulder.",
            "I make origami - fold paper, intricate patterns. Helps - sometimes.",
            "My hobby doesn't cause trouble. Just keeps my mind from spiraling."
          ],
          [
            "You're not wrong. Some days, safe means quiet corners.",
            "I fold origami. Patterns help me focus, especially lately.",
            "Difficult to find paper when supplies are tight after outages.",
            "The city's noise makes simple things complicated."
          ],
          [
            "Probably. Things have shifted since the tribunal fallout.",
            "Origami is my thing. I make cranes, tessellations - sometimes full modulars.",
            "The recent blackout forced me to finish one in the dark.",
            "Paper is hard to come by, but it matters to me.",
            "It's strange, folding when the world outside is falling apart.",
            "I find clarity in the patterns, even if nothing else makes sense."
          ],
          [
            "More like sidestepped a landslide. It's been... unpredictable since the broadcasts.",
            "I make origami - complicated designs, not just cranes. Layers, tessellations, abstract forms.",
            "When the power failed last week, I finished a model just by feel.",
            "People call folding childish. It isn't. It's controlled complexity, not chaos.",
            "The shortages since the tribunal make it harder, but I ration paper anyway.",
            "Some nights, folding is the only thing that keeps my anxiety manageable.",
            "I keep my models hidden. Even a hobby can raise questions lately."
          ],
          [
            "Ducking trouble feels second nature after this month. The tribunal put a spotlight on everyone, me included.",
            "Origami is my outlet. I fold elaborate tessellations - modular polyhedra, insects, never just simple cranes.",
            "Paper's almost contraband with the shortages. I salvage old forms, official notices - sometimes even tribunal documents no one will miss.",
            "During the blackout, finishing a folding cycle by lamplight felt... like reclaiming something normal.",
            "Most people think it's pointless. But for me, origami is pattern and predictability - not at all like living with a variable BCI.",
            "After the tribunal, neighbors whispered about 'snitches' and 'heroes.' I just kept folding. Quiet action is the only place I still have control.",
            "I hide my models in plain sight now, mostly out of defiance, maybe habit.",
            "Funny - these days, every crease feels like its own kind of resistance."
          ]
        ],
        "hobby_answer": [
          [
            "Yeah. Still origami.",
            "Just helps to keep busy, you know.",
            "Materials are harder to find. Blackout interrupted a piece.",
            "That's all."
          ],
          [
            "It is. Safer than politics.",
            "I just needed something quiet after the tribunal.",
            "Paper's short supply now - people hoarding everything.",
            "Lights cut mid-fold yesterday. Lost my place.",
            "Trying to keep routine."
          ],
          [
            "Yes, still folding cranes and tessellations.",
            "It's better than thinking about the BCI half the time.",
            "Blackout last night nearly ruined my latest model.",
            "You can't concentrate with people yelling about restitution in the hallway.",
            "Still, it gives me a pattern I can finish.",
            "At least that's within my control.",
            "Helps push out everything else."
          ],
          [
            "Yeah, definitely still my shield.",
            "Folding paper helps me block out BCI nightmares.",
            "That blackout pushed me to finish a crane by candlelight.",
            "Voices outside quoting my testimony - almost broke my focus.",
            "Paper's scarce, but routine matters now more than ever.",
            "Each fold felt deliberate, like proof I could create something stable.",
            "Right now, even that small control is resistance.",
            "Origami never judges, never rewrites outcomes."
          ],
          [
            "Always my shield. Origami's been habit since I started at Directorate.",
            "After testifying, I folded a crane with shaking hands - paper's from old ledger sheets.",
            "When the blackout hit, I kept going. Candles, creased edges - I wanted it finished no matter what.",
            "You can't hide from your public role, but you can still finish a fold.",
            "Heard my own name in the stairwell - familiar and strange.",
            "The process calms me even now, when BCI's errors keep me up.",
            "People hoard paper, fear new shortages, and yet I keep scavenging.",
            "Sometimes I think the system fears unused potential - origami is proof of something else.",
            "Making something out of scrap helps, especially when trust in everything else breaks."
          ]
        ]
      },
      "main": {
        "main": {
          "opener": "You keeping out of the mess, or does it keep finding you?",
          "variants": [
            [
              "Hard to stay clear when things keep shifting.",
              "I... had to show up at that tribunal they ran on the feeds.",
              "Shared what I had to, about errors in the system.",
              "Now people look at me differently. That's all."
            ],
            [
              "Trouble found me, I guess.",
              "I gave testimony at the city tribunal. They wanted someone to talk about BCI mistakes.",
              "I only said what was on record, but it got... attention.",
              "Things are complicated at work. People keep their distance.",
              "Feels like I'm walking around with a target on my back."
            ],
            [
              "Seems like the mess picks its own targets. I couldn't dodge it.",
              "They called me to testify - about the BCI, about silenced mistakes.",
              "Security took me in, kept me moving just for the cameras.",
              "My statements, they called them whistleblowing. I didn't, not really.",
              "Now there's attention - lots of it. Some say I helped, others blame me for everything.",
              "Since then, my score budged. Not enough to matter."
            ],
            [
              "Mess found me this time, and I let it.",
              "I testified about the BCI hiding its own mistakes, about people losing access for no real reason.",
              "Security kept me under watch, steering me from my home to that tribunal.",
              "My old colleagues went quiet overnight. Feels like I disappeared just by speaking up.",
              "Media calls me a whistleblower but skips what it's like living under Directorate surveillance now.",
              "They nudged my score up - like it helps - because I did what they asked.",
              "Can't tell if anything's better or just... changed shape."
            ],
            [
              "The mess is inescapable now - especially since I stepped right into it.",
              "I used to believe in the system, that it kept the worst away. But I've seen too many quiet denials, too many errors erased.",
              "Testifying... it wasn't courage, more like the last option. I told them everything: cover-ups, the real number of people shut out.",
              "Security put me in a bubble before and after. My neighbors avoid me. At work, doors stay closed.",
              "They call me a whistleblower on the feeds. They don't show the aftermath - Directorate keeps me monitored, every call, every trip.",
              "My BCI score is up, officially. Unofficially, I'm circled in red.",
              "Sometimes I wonder if the Innovators - my own - are any different now that the pressure's on.",
              "All that's left is the risk and the hope... maybe what I did shifts something, even if I can't see it now."
            ]
          ],
          "emotion": "unsteady, exposed but resolute"
        },
        "emotional": {
          "opener": "Oksana, none of this is your fault. You did what was right, even when it cost you. Some people notice. I notice.",
          "variants": [
            [
              "Thank you. That matters.",
              "Sometimes I forget anyone does."
            ],
            [
              "It helps, hearing that from someone who sees me.",
              "Most people just look away. I appreciate your words.",
              "I don't talk about this much."
            ],
            [
              "You saying that... it reminds me I'm not completely alone here.",
              "Most days, it's hard to keep perspective.",
              "But I needed to hear it, honestly.",
              "Sometimes, it feels like the system erases people one inconvenience at a time."
            ],
            [
              "I'm surprised how much it helps to be seen, truly seen, even for a moment.",
              "Most of the time, I don't know if I'm doing the right thing or just surviving.",
              "I used to trust the system. Now, I question almost everything.",
              "It's strange - how much silence there is, even when it's loud everywhere else.",
              "Your words make it easier to breathe tonight."
            ],
            [
              "Honestly, I haven't felt understood in a long time. I used to measure everything, weighing what could go wrong, but you - well, you just listen.",
              "I keep thinking about why I stayed so loyal, even when it made no sense.",
              "This city, it teaches you to disappear... not just from others, from yourself.",
              "I won't pretend I'm brave. Half the time I just feel tired.",
              "But someone noticing, even quietly, reminds me what it felt like to matter.",
              "If more people thought like you, maybe Stenograd would be different."
            ]
          ]
        },
        "factual": {
          "opener": "What does it even matter? Tribunal or not, the city's still coming apart. No one really knows what's happening behind those doors - unless you do.",
          "variants": [
            [
              "Systems keep failing. Council keeps saying it's contained.",
              "Labor roles are mixed up, nothing makes sense anymore.",
              "Feels like some people just vanished then came back, causing more trouble.",
              "Public doesn't hear half of it.",
              "Nobody trusts the feeds."
            ],
            [
              "Things are worse than on the feeds. Blackouts, labor chaos, people reappearing.",
              "Council blames the old system faults. Nobody claims real responsibility.",
              "Saw manual rerouting scripts run wild - wrong people locked out, others suddenly in charge.",
              "A mural started unrest. Directorate cracks down, but Innovators keep pushing change.",
              "No one knows what's next. Not from inside."
            ],
            [
              "The blackout showed everyone how shaky things are.",
              "Even trusted citizens have lost access privileges - BCI churned itself inside out for days.",
              "AI rerouted high scores to menial tasks, dropped outliers into sensitive posts. Total disorder.",
              "Invisible groups resurfaced. They're organized, not like before. Exploiting gaps in oversight.",
              "Council factions are at each other's throats, Innovators blamed for leaks but demanding reform.",
              "People line up to see Halden's mural. Feeds claim it's subversive, but it's just reminding everyone who built this machine.",
              "Sometimes I think the only fix would be to start over. Quietly, nobody says it."
            ],
            [
              "Ledger got out - Halden tracked BCI abuses, silent erasures. It proves what a lot of us suspected but couldn't say out loud.",
              "That mural, the night of the blackout, changed something. People talk strategies now, not just rumors. New groups surface, fighting for lost odds.",
              "Council's lost control of the story. Innovators want overhaul - they pretend at repairs but most don't want to go back to how things were.",
              "Everyday routines are breaking down. Nobody trusts assignments, nobody trusts the Council's intent.",
              "Directorate pressure is up but people push back, even public servants. Feeds don't show it.",
              "My team used to believe new tech fixed things. Now we log errors and hope no one notices what we really think.",
              "If this ends, it'll be because someone on the inside - someone like us - had enough.",
              "It isn't loyalty anymore. Just risk, and the need to see change."
            ],
            [
              "I've seen the backend - BCI scores are still volatile. Code patches make it worse, not better. We document gaps, but only the boldest Innovators push to make it public.",
              "Halden's private archive opened a floodgate: The Ledger. I spent nights reading names, histories erased for nothing, entire chains of sanction built on faulty data.",
              "When those dissidents hacked the system, it felt like chaos for the feeds, but inside, it was relief. Finally, people saw what automatic governance really meant.",
              "Council infighting got ugly - Harmonists want stasis, Innovators split between controlled fixes and burning it all down. Directorate just enforces, no vision at all.",
              "I worked on error suppression - orders from above. When the tribunal started, my inbox filled with panicked coders trying to cover their patches.",
              "Public unrest is organized now. The mural gave them a symbol, but the data is what changed their minds. Reparations are coming, but the system resists every step.",
              "Nobody trusts the Council selection anymore. I've seen Innovator applicants blocked for being too critical - even with perfect scores.",
              "I can't go back to thinking the system just needs updates. The problems are in the structure.",
              "After Halden, we're all guessing. But hope's louder than fear lately. Especially among those who saw the real audit trails."
            ]
          ]
        }
      }
    },
    "shalek": {
      "opener": {
        "customer_id": "shalek",
        "questions": {
          "neutral": "Looks like you needed a pause - that right?",
          "hobby": [
            {
              "correct": true,
              "message": "You still hunting political literature no one's supposed to find?"
            },
            {
              "correct": false,
              "message": "Origami's still better than meds, huh?"
            },
            {
              "correct": false,
              "message": "Urban exploration or just drinking underground?"
            }
          ]
        },
        "wrong_hobby_answer": "That's not me. In free time, I collect political literature. It's a reminder of what was lost.",
        "neutral_answer": [
          [
            "Pause? Something like that. My hobby keeps me occupied. Collecting rare books, nothing extravagant. Recent events make everything slower, less predictable."
          ],
          [
            "Yes, a break is overdue. I restore banned political books - old habit from better days.",
            "The tribunal's been inconvenient. Harder to find quiet time for it.",
            "Not risking much tonight. Just needed a little distance.",
            "Even libraries feel watched now. It's tedious."
          ],
          [
            "Pause is right. I spend hours restoring and cataloguing banned political literature - bit of an obsession.",
            "With all this tribunal noise, privacy's nonexistent.",
            "I tried working on a 2041 pamphlet last night. Got interrupted by a compliance audit.",
            "Bright side, I salvaged a rare edition before they arrived.",
            "Strange days for book-lovers."
          ],
          [
            "You read me. Most evenings I'm home, restoring and memorizing banned manifestos and tracts.",
            "Last night's tribunal stirred up security audits - the timing couldn't be worse.",
            "I stash the rarest texts, recite passages just in case I lose them.",
            "Every new directive makes me more careful. Feels like preservation is war now.",
            "It isn't about nostalgia. It's about keeping honest words alive.",
            "Even when inspectors knock, I never forget what I've read.",
            "That's why I needed a break tonight."
          ],
          [
            "I needed the pause. My sanctuary is banned political literature - especially the texts no one dares cite.",
            "I memorize entire manifestos, keep multiple editions. Some are missing half their pages.",
            "After Oksana's testimony, compliance patrols swept my block. I had to hide everything important.",
            "I've built a secret archive over twenty years. Each inspection puts it at risk.",
            "Hardest part is knowing what to trust - editions differ, footnotes vanish like people did under the BCI.",
            "Last week, I smuggled a pre-BCI pamphlet for restoration. That felt almost defiant.",
            "They call it 'hoarding subversive history.' I call it refusing erasure.",
            "These days, every page feels heavier. I drink here to steady my hands."
          ]
        ],
        "hobby_answer": [
          [
            "Still does. Just quietly.",
            "Books don't vanish, even when screens go black.",
            "I keep what matters tucked away.",
            "Some nights, you hear patrols linger longer.",
            "That tribunal made even paper seem dangerous."
          ],
          [
            "Whispering, yes. Though sometimes it sounds more like warning than comfort.",
            "I don't display the rare titles these days.",
            "Lintz's testimony made my shelves feel heavier, somehow.",
            "Drones circle more often since the tribunal.",
            "I limit my reading to poetry when the Archive goes offline.",
            "It's not paranoia if they're truly watching."
          ],
          [
            "They whisper, and sometimes they scream.",
            "I reorganized half the collection after the testimony went public.",
            "Had to hide certain editions during last week's random audit.",
            "Temporary clamps on the Thought Archive; digital backups, worthless for now.",
            "What was just a pastime now feels close to evidence.",
            "Never thought I'd need muscle memory just to recite an old preamble.",
            "It's ironic  -  history turning contraband in real time."
          ],
          [
            "Always whispering, yes. Though, after the tribunal, even louder.",
            "Spent hours hiding first editions when compliance came knocking last week.",
            "My hands shook more than the inspector noticed, I think.",
            "I caught myself reciting passages under my breath, just to hold on.",
            "The Archive's locked tight, so only memory and paper survive.",
            "Hard to believe words could feel so fragile after all this time.",
            "Lintz's testimony left me shelving hope with caution.",
            "What used to soothe nerves now reminds me how thin the walls are."
          ],
          [
            "Still whispering. Louder than system alarms, if you know which words to keep.",
            "I started collecting when Marek Halden was still coding the first BCI subsystems.",
            "Had my first real scare last week  -  random search, just minutes after the tribunal aired.",
            "I hid more than books. I hid parts of myself, just in case.",
            "Whole authors redacted from the Archive overnight. I have their last printed words.",
            "The anxiety is new. Not about the officials, but about losing the language altogether.",
            "Sometimes I read aloud, just to believe what's left is real.",
            "When the city blacked out, I imagined the shelves breathing for me.",
            "This hobby was always defiance, but lately, it feels like rescue work."
          ]
        ]
      },
      "main": {
        "main": {
          "opener": "You still keeping the same rhythm, or things gotten weird?",
          "variants": [
            [
              "Rhythm is a luxury these days. Things changed after the tribunal broadcast. Direct orders come with fewer explanations now. I keep my head down. Everything feels strange now, as if the city is holding its breath."
            ],
            [
              "Routine isn't worth much lately. I was pulled into a last-minute Directorate review after the testimony fallout. Had to rewrite the usual lines, but this time they asked for everything about the BCI to sound vague. A few colleagues vanished. I think they flagged me. Everything feels strange now, as if the city is holding its breath."
            ],
            [
              "Nothing runs like clockwork anymore. After Oksana's testimony, I got summoned - new people, tighter scrutiny. Every statement about the BCI had to be cleaned, no more talk of certainty. Our office shrunk overnight; names peeled off the doors. They shaved my BCI for supposed 'withholding.' You start to question your own record. Everything feels strange now, as if the city is holding its breath."
            ],
            [
              "If rhythm means certainty, then no, it's gone. I write the words they feed the city, but lately nothing I send feels honest. The Directorate called me in - stripped away any illusion of infallibility from my drafts, pulled colleagues for reviews. A few disappeared. I worked alone, no access to my own archives. The BCI nipped me too, called it 'information withholding.' You wonder who's actually controlling this anymore. Everything feels strange now, as if the city is holding its breath."
            ],
            [
              "Same rhythm? That's almost a joke now. Since Marek's death, everything's off-kilter. One day I'm writing scripts for order, the next - dragged before security, told to erase the system's perfection from every phrase. My Directorate ties mean nothing when no one trusts each other. Colleagues - old hands, loyal - swept into silence. All signals point to fracture. My own BCI dipped; now I watch myself at work and at home. I've spent years dressing power in certainties and now - they want uncertainty to be the new truth. Everything feels strange now, as if the city is holding its breath."
            ]
          ],
          "emotion": "Everything feels strange now, as if the city is holding its breath."
        },
        "emotional": {
          "opener": "It's strange, but I've always thought that even when the city feels silent, someone still notices. You're not the only one.",
          "variants": [
            [
              "Strange is one word for it. Silence has weight here."
            ],
            [
              "Some things slip through the cracks, even now. I suppose you notice them too."
            ],
            [
              "I appreciate that. Sometimes it's difficult to tell if anyone feels it, or if it's just me.",
              "The quiet can be louder than the noise these days.",
              "Maybe that's when you have to listen most closely."
            ],
            [
              "You're right. Sometimes the silence says more than any broadcast could.",
              "I find myself cataloguing these empty spaces, as if there's a pattern I'm missing.",
              "It helps to know someone else senses it too.",
              "There are days I wonder if that's all it takes to keep going."
            ],
            [
              "You're right. The city's silences always held a kind of warning, but now it's like an unfinished sentence.",
              "I've spent years shaping stories no one was meant to question, but lately, even I can't convince myself.",
              "When I walk home, I listen for the old repetitions, and it's the absences that feel loudest.",
              "Maybe this city has always needed someone to notice, if only to bear witness.",
              "It helps to admit it, honestly - if only in places like this.",
              "Thank you for reminding me that someone is watching besides myself."
            ]
          ]
        },
        "factual": {
          "opener": "People are talking. Tribunal or not, what actually changed? Give me something real, not just atmospherics.",
          "variants": [
            [
              "They announced that tribunal on every screen in the city. Talk of investigations, reparations, nothing concrete yet.",
              "Some say Oksana's testimony forced their hand. Council's still running the show, regardless.",
              "No one's been punished, as far as I know. That's all anyone needs to see.",
              "Innovators blame old code. Harmonists stay quiet. Directorate... keeps watch.",
              "People sense a shift, but the machinery grinds on."
            ],
            [
              "They're promising reparations now, though I haven't seen who gets what. Sounds temporary.",
              "Oksana Lintz took the stand - some call it brave, others call it politics. Doubt she moved the needle much.",
              "Council named scapegoats, then walked that back. No names. No admissions.",
              "Innovators still say it's the system's fault, not theirs. Directorate isn't fooled, but won't admit fractures.",
              "After the hack, behavioral scores swung, jobs switched. People unsettled, but nothing breaks in public.",
              "Underneath, some are exploiting gaps. Who can blame them?"
            ],
            [
              "When the BCI glitched, the right people ended up doing the wrong jobs. I had to rewrite Council statements to cover confusion.",
              "That old metro mural? It turned Halden into prophecy. Now, anyone with a grievance uses it for leverage - and the Directorate is watching more closely than ever.",
              "Waves of citizens 'ghosted' by the system reemerged. Quiet panic behind closed doors - cliques forming, old loyalties shifting.",
              "The Ledger leak rattled us. I saw some drafts, redacted. Generations erased by error, not choice - that's a new flavor of unrest.",
              "Public apology is off the table. Reparations are 'partial and pending.' That's the phrase I was told to use.",
              "Innovators push for upgrades. Harmonists want stasis. Directorate prefers hard lines - keeps the peace, or tries to.",
              "Order isn't the same as trust. That's being tested citywide."
            ],
            [
              "I spent twelve hours drafting statements for the Tribunal fallout. Every word weighed to balance blame without admitting guilt - especially with Directorate eyes on me.",
              "After that mural surfaced, Directorate wanted everything traced - who painted it, who saw it, who shared it. We're chasing ghosts, but it's political theater.",
              "They told us hush on The Ledger - too many ghosts from silent erasures. My own notes flagged in one sweep.",
              "Reparations: half measures, endless conditions. We skirt the word 'abuse' but everyone feels the bite.",
              "I met colleagues who vanished last month - now reassigned beneath new IDs. Some leaned into the chaos, others just want out.",
              "The BCI spikes, swings, shreds routines. Trust bleeds away, but the Directorate doubles down - contain, control, preserve the chain.",
              "Some Innovators want reforms, but they're maneuvering for power. Directorate circles wagons.",
              "We used to believe in engineering order. Now, my directives reek of survival."
            ],
            [
              "I've been in every messaging room since Halden's body was found. At first it was crisis management, now - it's pure contingency.",
              "The BCI labor shift sent engineers to clean streets, doctors to mines. My Directorate contacts had to suppress panics, issue reroutes.",
              "That mural... it was our reckoning. I ghostwrote a dozen disavowals, but the city wants myth, not denials.",
              "I helped redact The Ledger's worst. Saw erasures, scores erased from memory, lives denied - by our hand. My name's on half those old drafts.",
              "Colleagues disappeared after Tribunal prep. Some came back hollow, reassigned to handle 'contamination.'",
              "After the hack, we scrambled to reestablish control. Emergency lines jammed, but we spun it as 'adaptive resilience.' Didn't fool anyone.",
              "My BCI dipped after refusing to doctor one report. Directorate claims loyalty, but they'll flag their own.",
              "The Harmonists are sidelined, shuffled into irrelevancy. It's Innovators versus Directorate now - reformers and hardliners, neither trusted.",
              "I still prefer Directorate order. But now I guard my own words - trust is a tool, not a truth here."
            ]
          ]
        }
      }
    },
    "npetrak": {
      "opener": {
        "customer_id": "npetrak",
        "questions": {
          "neutral": "Did you time it well - calm right now?",
          "hobby": [
            {
              "correct": false,
              "message": "Political literature still keeping you up?"
            },
            {
              "correct": true,
              "message": "New typewriter on the bench?"
            },
            {
              "correct": false,
              "message": "What's your last origami fold say?"
            }
          ]
        },
        "wrong_hobby_answer": "That's not me. In free time, I collect antique typewriters. They remind me of a time when things were different.",
        "neutral_answer": [
          [
            "Timed, perhaps. Not a fan of crowds these days.",
            "I restore antique typewriters in my quiet hours.",
            "Most wouldn't see the appeal or the point. Suits me fine.",
            "Recent disruptions haven't helped maintenance routines."
          ],
          [
            "Timing is everything now. Too much noise lately.",
            "My hobby's restoring old typewriters. Keeps the mind steady.",
            "Used to borrow parts from others - now that's... less reliable.",
            "Compensation seekers keep turning up, interfering with the work.",
            "I prefer being left to my repairs and my notes."
          ],
          [
            "Quiet is rare these days. I use it to work on my typewriters.",
            "Restoring antiques is my hobby. Old keys, the satisfaction of ribbon alignment.",
            "Had a mishap thanks to a neighbor filing a compensation form.",
            "She tapped away, smudged the platen. System chaos spills into everything lately.",
            "Funny, even hobbies get swept up in these reforms.",
            "Not many left who understand the difference between Olympia and Erika."
          ],
          [
            "Yes, I watch for calmer hours just to return to my typewriters.",
            "Restoration - mechanical, not digital. Each key springs back a century.",
            "Last week, Elena, new on the registry, borrowed my Erica for forms.",
            "More and more people want hard copies. Tribunal reparations, you see.",
            "It's odd - old machines feel suddenly important again. Like a peculiar currency.",
            "I track precise dates for each repair. Even that raises system alerts now.",
            "Sometimes, I miss when these things were overlooked. Noise, but harmless."
          ],
          [
            "I time these visits for peace - reminds me of fixing typewriters late at night.",
            "It's what I do: antique typewriter restoration, real mechanics - each machine with its story.",
            "After the reparations tribunal, neighbors started needing actual documents, not just data.",
            "Just last week, my Erica produced formal copies for someone 'reinstated' after years erased.",
            "Used to be a private ritual. Now I clean bureaucratic fingerprints from the keys.",
            "I keep a handwritten log for each project - ironic, given the city's surveillance zeal.",
            "Last blackout, I restored an Olympia in candlelight. The city almost felt human.",
            "Sometimes I wonder if these old keys remember what's been silenced."
          ]
        ],
        "hobby_answer": [
          [
            "Still keeping the collection, yes.",
            "They don't make them like they used to.",
            "Lately, too many people interested in paper records.",
            "Tribunal's made things...unpredictable.",
            "Hard to enjoy old habits these days."
          ],
          [
            "Still have a few, yes. Mostly for my own notes.",
            "Restoring an Erica, though supplies are harder to find now.",
            "After that mural - more eyes on anything off-network.",
            "Council bulletin shook up the block. Some old tenants reappeared.",
            "Had a stranger ask to use my typewriter, said compensation forms needed it.",
            "Not the kind of attention I want."
          ],
          [
            "Yes, still collecting. Working on an old German Erica model now.",
            "I like keeping my notes off the terminals.",
            "After the tribunal statements, folks started showing up with Council paperwork.",
            "One neighbor - gone for years - asked to use my typewriter for appeals.",
            "I obliged, though it felt odd.",
            "Feels like private hobbies are less private now.",
            "Guess system changes ripple into every corner."
          ],
          [
            "Still collecting, though these days it's more for the ritual than the function.",
            "Restoration keeps my hands steady. I still type my journals.",
            "Now, since the tribunal, everyone's chasing old records or forms.",
            "Had someone return just to borrow my ribbon for compensation papers.",
            "She hadn't touched a typewriter in years, but thought paper might reach them.",
            "The BCI never tracked keystrokes, but now even ink attracts notice.",
            "Hard not to feel exposed, even fixing small machines at home.",
            "Strange how chaos can reach the quietest corners."
          ],
          [
            "You know it, Alex. Still have seven in the flat - each with its own quirks.",
            "I picked up the hobby years before the BCI. Paper felt honest.",
            "These days, keeping one is almost subversive. More so after Halden's mural incident.",
            "Since the tribunal, old neighbors have re-emerged looking for ways to leave a trace.",
            "One borrowed my typewriter for Council compensation. Her hands shook harder than the carriage did.",
            "Strange, seeing analog fear in digital times.",
            "The BCI never knew how to read erasures or overwritten lines.",
            "But now, with everyone scrambling for justice, even keys feel suspect.",
            "I clean them out of habit, but some ink never fades from a system like this."
          ]
        ]
      },
      "main": {
        "main": {
          "opener": "Funny how things shift without anyone saying much. You seen that around you?",
          "variants": [
            [
              "Shifts, yes. Hard not to notice them now.",
              "Schedules used to keep the building in order. These days, things arrive out of place.",
              "People you thought had moved on come back, paperwork in hand.",
              "Feels stranger every morning. That's all."
            ],
            [
              "Shifts, yes. Hard not to notice them now.",
              "They talk reparations, but systems only respond with delays.",
              "Saw some faces I'd not expected, all claiming new rights.",
              "I keep to myself. Too many opinions fly around here now.",
              "Strange, how a routine can unravel. Makes you rethink what's really stable."
            ],
            [
              "Things do change quietly, don't they.",
              "After the Council's announcement, old neighbors turned up. People disappeared from records came back, expecting reparations.",
              "Routine's off now. Deliveries arrive whenever. No one knows if they're still on a list.",
              "I avoid the common rooms when it's busy. Some things are better not overheard.",
              "Checking Council bulletins for updates is just habit at this point.",
              "My score dipped again. Seems system doesn't like watchfulness."
            ],
            [
              "Quiet shifts, yes... hard to ignore if you've worked close to the Council.",
              "After the reparations talk, tenants who'd vanished showed up, demanding what they're owed.",
              "Regular building services fell out of step. The hallways feel tense.",
              "I've grown careful - changing my movements, keeping away from arguments about fairness.",
              "Nowadays, I watch Council bulletins, hoping for a clear word, but you mostly get noise.",
              "All that caution? The system caught on. Dropped my BCI again, for simply not wanting trouble.",
              "Feels like even doing less is risky now. Like the city wants you to act casual in the dark."
            ],
            [
              "Strange times... You work long enough in the Council's shadow, you grow sensitive to these undercurrents.",
              "Now, after those broadcast promises about repair and justice, familiar faces reemerged as if from thin air.",
              "Disappeared neighbors walking corridor like nothing happened - claiming their compensation, stirring the air.",
              "The routine's gone - services forgot us, deliveries a mess, no more predictability left. That's a system trying to keep order by making it up as it goes.",
              "I avoid the trading of grievances. Just being seen with the wrong group can tip the scale. I learned to keep mostly to myself.",
              "My only source left is Council bulletins, read from home, quietly, but the more I check, the more the system flags me.",
              "Old instincts kick in - never be the first, never the loudest. Each report, each absence, marks you somehow.",
              "I've always preferred quiet stability, like the Harmonists. Hard to see where it leads now. Weary, yes. But habits linger. Maybe there's a use for that."
            ]
          ],
          "emotion": "weary but quietly hopeful"
        },
        "emotional": {
          "opener": "Nikola, you aren't invisible here, and your caution makes sense. People like you deserve a place that doesn't ask them to vanish.",
          "variants": [
            [
              "That's generous of you to say.",
              "People notice more than they admit."
            ],
            [
              "I appreciate the sentiment.",
              "Sometimes it's easier to be overlooked. Keeps things smooth, usually.",
              "You read people well, Alex."
            ],
            [
              "Thank you. It's not common to hear that.",
              "Fading into the background... it wears on a person, even if it's sometimes safer.",
              "Most prefer to ignore what's in front of them. You don't.",
              "It's reassuring, in a way."
            ],
            [
              "That helps more than you know.",
              "It's hard to balance caution and hope, but hearing that - makes it feel possible.",
              "Over the years, you learn to make yourself small. Still, being seen matters.",
              "I suppose I miss when trust was simpler.",
              "You seem to understand the weight some carry."
            ],
            [
              "You have a rare kindness, Alex. It makes a difference.",
              "I spent my best years in rooms where silence kept you safe. Now, silence feels heavy.",
              "The world teaches you to shrink, to tidy away anything uncertain or inconvenient.",
              "Still, moments like this remind me what it was like to feel included - genuine, not just tolerated.",
              "We tell ourselves adaptation is neutral, but it costs you, quietly.",
              "Thank you for reminding me I'm still here, and that it matters."
            ]
          ]
        },
        "factual": {
          "opener": "Everyone's got an opinion, but you were close to the Council. What do you really make of all this upheaval?",
          "variants": [
            [
              "Council wants us watching the tribunals. Keeps eyes forward, not sideways.",
              "BCI upsets, sudden job trades. Most handle it as best they can.",
              "Hard to say what's changing, honestly."
            ],
            [
              "Tribunals make fine drama, but you notice the real shuffling in the background.",
              "Labor's been reassigned all wrong - order gone, but maybe that's the point.",
              "Council signals make things sound under control, but I wouldn't bet on it.",
              "Some who vanished turned up. That unsettles people."
            ],
            [
              "Citizens saw their scores swing overnight. You try to keep up, but it's chaos.",
              "Labor placement's a mess. People suited for nothing getting serious posts.",
              "Tribunal show - looks like accountability, but the Council keeps it on their ground.",
              "Suddenly, the disappeared come back with claims in hand. Doesn't feel resolved to me.",
              "You watch, you realize: compromise, not restoration.",
              "Never saw much patience for disorder, not among Harmonists anyway."
            ],
            [
              "They make the tribunal public, talk 'remedial intent,' but it's all signals, no real core admission.",
              "Lots of new 'official' faces fighting for reparations - old absences swept in.",
              "When high-score citizens are upended, makes you question the logic of it all.",
              "Council fractions louder now. Directorate stirs hard, Innovators spin the story. Harmonists left watching.",
              "I spent years proofing Council statements. Saw how they sideline what doesn't fit the narrative.",
              "Never meant to see things unravel, not with a Harmonist's lean. Still, you hold out for the old routines - maybe something useful left."
            ],
            [
              "Watched it often: staged accountability. The Council always stacks the deck, even now with the tribunals.",
              "Innovators crack Halden's archives. Ledger comes out - decades erased without record. Nothing new, just exposed.",
              "Neighborhoods organize quietly now; the system's lost its mask.",
              "I manage bulletins, but there's no order to what's left. Reassignments, vanished neighbors, all thrown together by a failed logic.",
              "Directorate doubles down on its grip. Innovators want transparencies. Harmonists sidelined - no taste for spectacle, just stability lost.",
              "I used to pass Council memos along. Saw the edits, what went missing between drafts.",
              "You learn to read noise for what it is. I kept faith in slow repair - stability above all. That's where I leaned, still do, quietly.",
              "People think chaos came from nowhere. But these cracks were set in the system's bones, long before Halden's shadow showed up.",
              "Hard to abandon hope, even now. Habits linger, even the good ones."
            ]
          ]
        }
      },
      "decision": {
        "preference": "a",
        "dilemma": {
          "opener": "That exhale - something behind it?",
          "variants": [
            [
              "Strange days. Some things aren't lining up the way they should.",
              "Too many eyes, not enough quiet corners anymore.",
              "Between doing nothing and doing something I can't take back."
            ],
            [
              "A choice landed in my lap. Both ways, it's a mess.",
              "I can let the gears grind to a halt, or loosen them altogether.",
              "Either restores quiet or invites a storm. Can't tell what's worse.",
              "One will keep order, the other throws the door wide open."
            ],
            [
              "There's a breach only a handful know about. Serious. Could upend everything.",
              "I could back shutting everything down, just for a pause. Give the city time to think.",
              "Or I could help those who slipped through, hand them the keys to the locks.",
              "Both carry risks - order might collapse, or trust in the system may vanish for good.",
              "Neither sits comfortably. Each promises change I can't predict."
            ],
            [
              "Security breach in the archives - messy, dangerous, and not by chance.",
              "The Directorate wants the city dark, scores off, everyone on their own for a while.",
              "Other path - give the vanished what they need to step out, own their silence.",
              "Backing the blackout means holding my Harmonist leanings, keeping order above all.",
              "Helping the vanished means trusting people to build something new, no safety net.",
              "A BCI score like mine, I'm watched either way. Old loyalties only go so far."
            ],
            [
              "I've lived so long by the rules, even as I copied secrets by candlelight.",
              "Now I have to pick: freeze the city, let shadows run wild, or shine a light where it hurts.",
              "The blackout favors order, keeps the Council afloat, even if it means more silence.",
              "The other option hands future to those erased - if they build something better or burn it all is anyone's guess.",
              "Harmonist in me wants transition, not chaos. But talk with you, Alex, made me see the cracks - the faces, the cost.",
              "My BCI hangs by a thread. I'm trusted by no one, but still hold the keys.",
              "Not sure which regret I can carry longer. Maybe there's only survival, not right or wrong."
            ]
          ]
        },
        "belief_a": [
          {
            "belief": "Order must be restored before any real reform can happen.",
            "monologue": [
              "If the city dissolves into confusion, we lose the ground for any change.",
              "Without a basic shape to things, correction turns to chaos, not progress.",
              "In Stenograd, loose ends become calamities; first you steady the vessel, then you steer."
            ],
            "supportive_response": [
              "You're right - easing disorder only fuels panic and fear in people's minds.",
              "It makes sense to steady things first. Go on, I'm listening."
            ],
            "challenging_response": [
              "Suppose order's just a cover for more mistakes - when do you draw the line?",
              "I wonder if order means anything if people never truly heal. Please, continue."
            ]
          },
          {
            "belief": "Change must be managed slowly, with minimal risk.",
            "monologue": [
              "A rushed shift breaks more than it mends; we know how that story ends.",
              "If we push too hard now, the city could unravel beyond our reach.",
              "Part of me trusts time more than any lever - the slow current rarely betrays."
            ],
            "supportive_response": [
              "A cautious hand repairs more than it destroys, especially in a place like this.",
              "Patience often saves what haste ruins. Please, share the next thought."
            ],
            "challenging_response": [
              "But sometimes slow change just preserves the rot - haven't we seen enough delays?",
              "What if waiting makes things worse, not safer? Go on, I want to hear more."
            ]
          },
          {
            "belief": "Public trust requires some measure of continuity, even if imperfect.",
            "monologue": [
              "People need something familiar - even flawed - to cling to, when the world tilts.",
              "To tear away everything at once is to breed only suspicion and resentment.",
              "We risk losing the city's faith entirely if we erase too much, too soon."
            ],
            "supportive_response": [
              "Continuity gives people hope, even if it's an imperfect anchor in a storm.",
              "Familiar ground steadies the heart. Let's keep going with your thoughts."
            ],
            "challenging_response": [
              "But sometimes holding on just builds bitterness - maybe it's time to let go?",
              "What if faith returns when the curtain drops on old habits? Keep going, this is important."
            ]
          }
        ],
        "belief_b": [
          {
            "belief": "Truth must come before order, even if it is painful.",
            "monologue": [
              "Order is what kept the city breathing, but we can't patch over every crack with silence.",
              "If we bury the truth now, the same rot returns somewhere else, just deeper underground.",
              "Sometimes revealing what happened is more dangerous than any blackout, but some things must see daylight."
            ],
            "supportive_response": [
              "That kind of honesty is rare, especially here in Stenograd.",
              "Go on, I'd like to hear what else you've been thinking."
            ],
            "challenging_response": [
              "Truth isn't much comfort if it leaves nothing standing afterwards.",
              "Tell me why you think this kind of risk is worth it - I'm listening."
            ]
          },
          {
            "belief": "The people have a right to reclaim their own civic destiny.",
            "monologue": [
              "You can only hold a city together with enforced routines for so long before it splits at the seams.",
              "People have been managed like numbers, shuffled from queue to queue, as if that was living.",
              "If we don't hand some choices back to them now, maybe they never get that chance again."
            ],
            "supportive_response": [
              "You've seen more than most - if anyone can say this, it's you.",
              "What happened next? I'm curious what makes you weigh that so heavily."
            ],
            "challenging_response": [
              "But what if the city tears itself apart when you loosen the grip?",
              "It sounds right, but is Stenograd even ready to decide for itself?"
            ]
          },
          {
            "belief": "Old systems built on secrecy must be openly challenged to heal.",
            "monologue": [
              "I've carried secrets because I thought they kept things from collapsing, but maybe I was wrong.",
              "Letting the system hide its flaws only feeds resentment and fear - nothing mends in the dark.",
              "Exposing these shadows could invite chaos, but perhaps that's the only way Stenograd finds balance again."
            ],
            "supportive_response": [
              "You know your history - secrets rarely age well in this place.",
              "Keep going. I'm interested how you see that playing out now."
            ],
            "challenging_response": [
              "Unmasking everything may not heal; sometimes wounds only deepen in daylight.",
              "Go on - how do you imagine rebuilding trust if all is suddenly out in the open?"
            ]
          }
        ],
        "decision": {
          "monologue_a": [
            [
              "I will act when the time comes.",
              "Plans are set in motion."
            ],
            [
              "The system's lights will go out for a while.",
              "There are reasons for a blackout."
            ],
            [
              "I will order the blackout as the Directorate asks.",
              "The city will organize itself in the dark.",
              "It's necessary to buy us time."
            ],
            [
              "I will pause BCI and trust citizens to adapt.",
              "The Directorate believes this blackout gives order time to recover.",
              "Others will have space to reconsider their roles.",
              "We need to step back and see what comes next."
            ],
            [
              "I will authorize the blackout and halt the digital scores for once.",
              "Your words about human costs stayed with me, Alex.",
              "The city will move without the system's shadow - maybe find something lost.",
              "When the power returns, so might a new kind of understanding."
            ]
          ],
          "monologue_b": [
            [
              "Certain people will find what they need.",
              "Some doors may open soon."
            ],
            [
              "Evidence might change hands soon enough.",
              "Those vanished may show up again."
            ],
            [
              "I'll slip the hidden protocols to the right hands.",
              "Vanished citizens will have their moment to appear.",
              "Let the city see something real again."
            ],
            [
              "I'll help the disappeared step forward, even if trust in the system breaks.",
              "You made me see how facts matter more than secrets.",
              "New non-score zones may take shape if I act now.",
              "Maybe that's the start of true repair."
            ],
            [
              "I will quietly arm the vanished with what I know, Alex.",
              "I owe Stenograd honesty after all these years.",
              "Your insistence opened my eyes to what secrecy costs souls.",
              "It could end the system as we know it, or begin renewal."
            ]
          ],
          "monologue_self": [
            [
              "I have decided.",
              "No further discussion is needed."
            ],
            [
              "It's done as is best for order.",
              "No one needs to know more."
            ],
            [
              "I will do as the Directorate proposes: a full system blackout.",
              "Citizens will have to adjust without guidance for now.",
              "The records stay safe another day."
            ],
            [
              "I'll support the blackout and pause BCI, even if it breeds confusion.",
              "Order above all, Alex. Tradition matters, even now.",
              "Sometimes one must be the quiet hand in chaos.",
              "I hope people forgive what they do not see."
            ],
            [
              "I'll carry out the blackout without waiting for advice, Alex.",
              "Old beliefs are hard to shed; gradual repair feels safer for Stenograd.",
              "Maybe I'm wrong to choose order over open change, but I can't help it.",
              "Even if I'm remembered as a caretaker, I'll guard what little balance remains."
            ]
          ]
        },
        "title_a": "The Great Silence",
        "title_b": "Echoes of the Vanished"
      }
    },
    "dtomenko": {
      "opener": {
        "customer_id": "dtomenko",
        "questions": {
          "neutral": "Did you make it through the noise?",
          "hobby": [
            {
              "correct": false,
              "message": "What's your last origami fold say?"
            },
            {
              "correct": false,
              "message": "Urban exploration or just avoiding work?"
            },
            {
              "correct": true,
              "message": "Freestyle FPV drones still keeping you sane?"
            }
          ]
        },
        "wrong_hobby_answer": "That's not me. In free time, I fly FPV drones. It's a way to escape the noise of the city.",
        "neutral_answer": [
          [
            "Yeah. Didn't bother me much.",
            "Spent the blackout flying. I do FPV drones.",
            "Helps pass the static left from tribunal coverage.",
            "It's quieter when no one's around."
          ],
          [
            "Got through it fine. Block's always noisy lately.",
            "I fly FPV drones, so blackout was good timing.",
            "Less interference meant cleaner signal for once.",
            "People keep talking about the tribunal - wasn't interested.",
            "No one came looking while I was flying."
          ],
          [
            "Yeah, made it. Blackout actually helped my hobby - FPV drone flying.",
            "Sector G's calmer when power's out. Way better for practicing rolls.",
            "Saw more pilots out than usual, probably hiding from the tribunal stuff.",
            "Signal jamming's less with half the grid down.",
            "We all just flew, tried not to think about BCI for a bit.",
            "Helps me clear my head."
          ],
          [
            "Yeah. I needed the noise to disappear for a while.",
            "My thing's FPV drone flying - real freedom when the grid's dark.",
            "Last night there were maybe a dozen of us in Sector G.",
            "No one talked much, but we all knew why we were out - get away from tribunal chatter.",
            "We streamed tribunal audio over the drones, just for atmosphere.",
            "Sometimes you forget everything's logged, blackout or not.",
            "For a couple hours, it was just flying and nothing else."
          ],
          [
            "Yeah, I did. Honestly, flying drones is the only thing that makes sense lately.",
            "Been doing FPV freestyle for years - grew up modding cheap quads with my brother.",
            "With BCI in chaos, signals are weird. Friday, we got a kind of drone pilot gathering - never planned.",
            "People projected that Halden mural on the wall. Some streamed tribunal audio to their goggles.",
            "We weren't just flying for fun. It felt like keeping a piece of the city for ourselves.",
            "I push my quad harder now - guess part of me wants to test what the system notices these days.",
            "Sometimes I still think about my brother when I fly these blackout runs.",
            "None of it's as anonymous as it looks, but for those flights, you almost believe it."
          ]
        ],
        "hobby_answer": [
          [
            "Yeah. Still fly sometimes.",
            "Only out in dead zones now.",
            "Too many watchers since tribunal started.",
            "Power cuts make it tricky.",
            "Less freedom to move, honestly."
          ],
          [
            "Still flying when I can.",
            "Harder since power failures - systems unstable everywhere.",
            "Others out there too, maybe more than before.",
            "Tribunal audio's even bleeding into our comms sometimes.",
            "People act different after mural showed up.",
            "Feels like the system's watching closer."
          ],
          [
            "Yeah, FPV flights clear my head.",
            "Last blackout, signal was a mess - too much interference.",
            "More pilots showing up at once, weird vibe lately.",
            "Saw the mural projection mid-flight. Changed the whole mood.",
            "Can't avoid tribunal talk, even in the air.",
            "Feels like we're being noticed more now.",
            "I keep it quiet, just stick to old patterns."
          ],
          [
            "Flying keeps me steady - especially now.",
            "Last weekend we crowded a dead zone, blackout made it safer.",
            "Someone streamed tribunal audio right to the headsets.",
            "We watched the mural flicker, felt part of something big.",
            "It's not just a hobby with the BCI failing like this.",
            "A lot of us push limits, maybe out of spite.",
            "The air feels heavier, like every move could be logged.",
            "I fly careful, but I miss how open it was."
          ],
          [
            "Yeah, it's still my therapy. Needed now more than ever.",
            "I hit Sector G during the blackout, crowd was bigger than usual.",
            "We all tuned in to tribunal chatter, just flying through the static.",
            "The mural - Halden unraveling - someone projected it. Whole group went silent.",
            "Some of us talked about lost friends, old scores wiped clean.",
            "BCI's glitching - means sometimes we slip through, sometimes we get flagged hard.",
            "Risk is high, but for a few hours, it feels like control.",
            "Funny, we act free, but I know every maneuver leaves a trace.",
            "I started this after my brother vanished in an audit. Now I won't stop."
          ]
        ]
      },
      "main": {
        "main": {
          "opener": "Folks don't always talk, but they carry plenty. You carrying much these days?",
          "variants": [
            [
              "I'm just keeping busy at work.",
              "A lot of people asking for new wristbands after the tribunal stuff.",
              "Supervisors want us to move fast and not ask questions.",
              "Feels like things are getting shakier, and that's enough for now."
            ],
            [
              "Mostly just getting through long shifts.",
              "A lot of folks showed up wanting their band data fixed after the tribunal news.",
              "We're told not to look too close, just swap things out.",
              "My BCI score dipped a bit from handling so many flagged files.",
              "Makes it harder to walk around with your head up. Feels off lately."
            ],
            [
              "Work's changed. People come in nervous, demanding new wristbands after hearing what the tribunal uncovered.",
              "Everyone's worried about what's in their history now that the Council is promising reparations.",
              "Supervisors want things quiet. We process requests, no extra checks.",
              "I used to help people clean up their records, but I've had to stop.",
              "There's talk of reforms, but I feel exposed. My BCI took a hit for how I handled files.",
              "Feels like everything's uncertain and my hands are tied."
            ],
            [
              "I can't shake this sense that things are slipping. My days at the lab used to be routine.",
              "Now people rush in, worried what the system holds against them after the tribunal broadcast.",
              "We're told to process requests, not investigate. The old rules don't mean much now.",
              "Some colleagues openly question what we did before, which just adds to the pressure.",
              "I've stopped helping in ways I used to. I'm worried someone will dig through my old fixes.",
              "My score's dropped. Makes every choice riskier. Like every move could be flagged.",
              "Feels like I'm holding my breath, waiting for something to collapse."
            ],
            [
              "Honestly, I never thought I'd see the lab this tense. After the tribunal and Oksana's testimony, everything shifted.",
              "People come in anxious, demanding clean wristbands and transparency, scared of what their data says about them.",
              "My team used to quietly help people with the system's messes - erase a red flag here, tweak something minor there.",
              "Now I'm scared my past adjustments will show up with all the audits and reforms being promised.",
              "Everyone's talking reforms, but I don't trust anything until the old systems are stripped out.",
              "I've always leaned toward the Innovators' side - new tech, more openness - but even they're just blaming the past now.",
              "My BCI dropped when I tried to keep up. Each point lost pushes you further out. I know what that means - my brother disappeared after a BCI audit.",
              "I guess all that pressure just sits in my chest. It's hard to remember who you can trust, or if you're even safe yourself."
            ]
          ],
          "emotion": "Unsettled, vulnerable - from uncertainty and fear that the ground could shift under me again."
        },
        "emotional": {
          "opener": "Daria, somehow you keep finding your footing, even when everything shifts beneath you. You're not alone in this. It's all right to just... be unsettled for a while. That doesn't make you weak. It just means you're still paying attention.",
          "variants": [
            [
              "Thanks for saying that.",
              "I'm just trying to get by like everyone else."
            ],
            [
              "Hard to say it out loud, but you're right.",
              "Most people just tell me to adapt. It helps to hear someone gets it.",
              "Things feel unstable lately."
            ],
            [
              "It does help, hearing that from someone who notices.",
              "I don't have a plan. I just keep moving until things settle.",
              "Honestly, I wish it felt less like everything was temporary.",
              "But maybe paying attention is all anyone can do."
            ],
            [
              "I usually try to keep things to myself, but I appreciate your words more than I can say.",
              "Everything changes so quickly, sometimes I just stop trusting my own footing.",
              "I remind myself to stay alert, stay quiet, but it wears you down.",
              "It's comforting knowing I'm not the only one who feels this instability.",
              "Maybe being unsettled just means I'm aware enough to care."
            ],
            [
              "Most days I just blend into the background, try not to get noticed.",
              "Ever since I was a kid here, I learned to read the signals, wait for the floor to shift.",
              "Sometimes it feels like only people on the outside ever get to feel stable.",
              "But you're right, noticing the ground moving under us - it keeps us alive, I think.",
              "Trying to ignore it would be dangerous.",
              "So, thanks for seeing that in me. It means more than you probably know."
            ]
          ]
        },
        "factual": {
          "opener": "Everyone's talking, but you're close to this stuff. What actually is going on out there?",
          "variants": [
            [
              "Council made a show of that tribunal. Promised some kind of reparations about BCI mistakes.",
              "Seems like people are still waiting for anything real. System isn't fixed.",
              "Reports keep coming out, but I don't know how much any of it changes."
            ],
            [
              "Tribunal's all over public screens lately. Council members dodging blame - usual story.",
              "They say they'll make amends, but the steps are vague.",
              "After that mural of Halden turned up, more people started acting out. Feels less stable every day.",
              "Some of the old vanished names reappeared, I think. Hard to know what's deliberate and what's just more errors."
            ],
            [
              "After Halden, everything kept breaking. People with low scores suddenly got control, while the 'trusted' couldn't do basic things.",
              "City blacked out for hours. That mural of Halden drew crowds, changed things.",
              "Suddenly, a bunch of disappeared folks showed up again, running networks under the city's nose.",
              "Innovators in Council released some 'Ledger' files, showing how BCI erased lives for years.",
              "Now Council's on trial, but it's the same officials promising change. I lean toward new tech making things right, but I don't know if anyone trusts the system now."
            ],
            [
              "The power failures, the mural - Halden was warning us about something hidden in the system. Not just errors, but deliberate losses.",
              "When the blackout hit, people saw how flimsy all this control is.",
              "I saw records of people I thought were wiped coming back, organizing things in gaps where the BCI fails.",
              "Innovators cracked through, showed how the system's been scrubbing people silently for decades.",
              "Council's blaming the past, but these algorithms are still running most things.",
              "Feels like everyone's just waiting for someone else to fix it.",
              "I always believed Innovators would push us somewhere better - now it's hard to tell who's really steering."
            ],
            [
              "BCI collapse was everywhere - systems were swapping jobs randomly. I saw high-tier staff taking out trash, flagged people running critical panels. Whole place upside down.",
              "When the blackout hit, I got locked in my lab for hours. Afterward, a wall came down and there was Halden's mural. Everyone kept talking about the shadow - like he was showing us what he tried to fight.",
              "I read some internal chatter - people who vanished in audits came back overnight, using admin loopholes to organize underground. That's all outside the official channels.",
              "Innovators dumped the Ledger. It wasn't just scoring mistakes, it was erasures - people scrubbed as if they never existed. My brother... might've been in there.",
              "Council trial's just for show. Promises of reparations, but nothing real yet.",
              "Most of the Harmonists have gone quiet, Directorate's doing sweeps, Innovators are all about PR now. I always trusted their drive, but now it's performative.",
              "Wearing a lower score, you feel it everywhere - in the way people step around you, in the way the system reroutes your life.",
              "After seeing what the algorithms are capable of, I can't trust the old certainties. I wanted reform - still do - but not like this.",
              "I know too much now to believe there's any return to normal."
            ]
          ]
        }
      }
    }
  }
}