{
  "title": "The Forgetting",
  "timestamp": "2025-06-16T19:04:00",
  "news": {
    "official": [
      {
        "image_id": "blank_display",
        "headline": "System Status Reset",
        "anchor_line": "Today, city officials confirm adjustments to record-keeping across all BCI services.",
        "contextual_reframing": "Routine upgrades and strategic data management underscore the ongoing commitment to public order and adaptability.",
        "image": "news/blank_display.jpg"
      },
      {
        "image_id": "crowd_spectacle",
        "headline": "Communal Response Unfolds",
        "anchor_line": "Residents gather peacefully as Stenograd transitions to a new phase of administration.",
        "contextual_reframing": "Community engagement remains strong as systems evolve, showcasing resilience and unity during technical transitions.",
        "image": "news/crowd_spectacle.jpg"
      },
      {
        "image_id": "data_skyline",
        "headline": "A New Civic Choice",
        "anchor_line": "A citywide referendum is announced, empowering citizens to help shape the next era of urban management.",
        "contextual_reframing": "Participatory governance enhances stability. Stenograd moves forward, balancing collective memory and systemic innovation.",
        "image": "news/data_skyline.jpg"
      }
    ],
    "underground": [
      {
        "image_id": "blank_display",
        "headline": "History Wiped Away",
        "anchor_line": "First the Harmony Reset, now our records vanish overnight.",
        "contextual_reframing": "No more BCI files. No more old scores. For some, freedom. For others, a chance for the Council to erase every mistake they made.",
        "image": "news/blank_display.jpg"
      },
      {
        "image_id": "ambiguous_talk",
        "headline": "Who Decides Now?",
        "anchor_line": "People fill the squares, not knowing if they're safe or in danger without score protections.",
        "contextual_reframing": "Confusion everywhere. Justice for abuses at risk as evidence disappears. Those who suffered might get nothing but silence.",
        "image": "news/ambiguous_talk.jpg"
      },
      {
        "image_id": "data_skyline",
        "headline": "Past or Future?",
        "anchor_line": "Rada leaks: Halden set the purge in motion himself, forcing us to pick - more control or no memory at all.",
        "contextual_reframing": "With the system gone, we stand at a crossroads. Rebuild the machines - or let Stenograd become whatever we dare to remember.",
        "image": "news/data_skyline.jpg"
      }
    ]
  },
  "visitors": [],
  "character_stats": {
    "olintz": {
      "bci_score": 15,
      "political_preference": "rebel",
      "bci_history": [
        51,
        48,
        47,
        46,
        42,
        42,
        44,
        49,
        44,
        49,
        52,
        34,
        34,
        34,
        34,
        15,
        15,
        15
      ]
    },
    "npetrak": {
      "bci_score": 59,
      "political_preference": "harmonists",
      "bci_history": [
        69,
        72,
        73,
        73,
        68,
        70,
        68,
        71,
        76,
        78,
        75,
        71,
        69,
        67,
        65,
        62,
        59,
        59
      ]
    },
    "dtomenko": {
      "bci_score": 43,
      "political_preference": "innovators",
      "bci_history": [
        53,
        58,
        57,
        61,
        58,
        55,
        57,
        57,
        57,
        62,
        67,
        63,
        61,
        57,
        54,
        51,
        47,
        43
      ]
    },
    "lkova": {
      "bci_score": 55,
      "political_preference": "innovators",
      "bci_history": [
        64,
        65,
        63,
        64,
        68,
        67,
        64,
        66,
        61,
        58,
        59,
        54,
        72,
        72,
        71,
        70,
        71,
        55
      ]
    },
    "shalek": {
      "bci_score": 70,
      "political_preference": "innovators",
      "bci_history": [
        94,
        95,
        93,
        90,
        87,
        84,
        88,
        84,
        85,
        85,
        82,
        80,
        78,
        76,
        74,
        72,
        70,
        70
      ]
    },
    "rmiskovic": {
      "bci_score": 0,
      "political_preference": "rebel",
      "bci_history": [
        24,
        27,
        23,
        18,
        20,
        20,
        22,
        26,
        31,
        35,
        40,
        37,
        34,
        17,
        2,
        2,
        0,
        0
      ]
    }
  },
  "chats": {}
}