[
  {
    "timestamp": "2025-05-23T08:00:00",
    "visibility": "public",
    "description": "Residents begin receiving enigmatic 'Halden directives' urging everything from peace to protest. Rumors of a 'ghost in the code' sweep the city."
  },
  {
    "timestamp": "2025-05-27T17:30:00",
    "visibility": "internal",
    "description": "A decision is reached to let the adaptive code spread; eyes turn to the BCI as it starts rewarding those following the new directives and flagging others."
  },
  {
    "timestamp": "2025-05-31T12:00:00",
    "visibility": "public",
    "description": "The city erupts in confusion and unrest as factions fight for the meaning and ownership of the 'Halden protocol.'"
  }
]